iot_coordinator/__init__.py
iot_coordinator/coordinator_pb2.py
iot_coordinator/coordinator_pb2_grpc.py
iot_coordinator-0.0.1.dist-info/LICENSE
iot_coordinator-0.0.1.dist-info/METADATA
iot_coordinator-0.0.1.dist-info/WHEEL
iot_coordinator-0.0.1.dist-info/top_level.txt
iot_coordinator-0.0.1.dist-info/RECORD
