Metadata-Version: 2.1
Name: iot-coordinator
Version: 0.0.1
Summary: IoT Coordinator - Python SDK
Home-page: https://github.com/losfair/iot-coordinator
Author: Heyang Zhou
Author-email: me@connected.direct
License: UNKNOWN
Platform: UNKNOWN
Classifier: Programming Language :: Python :: 3
Classifier: License :: OSI Approved :: MIT License
Classifier: Operating System :: OS Independent
